{
  "schemaVersion": 1,
  "id": "coeluriacore",
  "version": "${version}",
  "name": "CoeluriaCore",
  "description": "Personal mod that enhances Minecraft experience",
  "authors": [
    "TetraTheta"
  ],
  "contact": {
    "homepage": "https://www.curseforge.com/minecraft/mc-mods/coeluriacore",
    "sources": "https://github.com/TetraTheta/coeluria-core"
  },
  "license": "All Rights Reserved",
  "icon": "assets/coeluriacore/icon.png",
  "environment": "*",
  "entrypoints": {
    "main": [
      "io.github.tetratheta.coeluriacore.fabric.CoeluriaCoreFabric"
    ],
    "client": [
      "io.github.tetratheta.coeluriacore.fabric.client.CoeluriaCoreFabricClient"
    ]
  },
  "mixins": [
    "coeluriacore.mixins.json"
  ],
  "depends": {
    "fabricloader": ">=0.16.14",
    "minecraft": "~1.21.1",
    "java": ">=21",
    "architectury": ">=13.0.8",
    "": "*"
  }
}
